{
    "title": "Infineon Security Controller IFX_CCI_000003h, 000005h, 000008h, 00000Ch, 000013h, 000014h, 000015h, 00001Ch, 00001Dh, 000021h, 000022h H13 including the products from the second production line and optional software packages: Flash Loader, Asymmetric Crypto Library, Symmetric Cryptographic Library, Hardware Support Layer, Hash Crypto Library, Mifare Compatible Software, and CIPURSETM Crypto Library",
    "versions": {
        "eal": ["EAL6", "EAL 2", "EAL 4", "EAL 5", "EAL 1", "EAL 2+", "EAL5+", "EAL 6"],
        "rsa": ["RSA2048", "RSA4096"],
        "des": ["Triple-DES", "TDES"]
    },
    "table_of_contents": [
        ["A", "Certification", 6],
        ["1", "Preliminary Remarks", 6],
        ["2", "Specifications of the Certification Procedure", 6],
        ["3", "Recognition Agreements", 7],
        ["3.1", "European Recognition of CC – Certificates (SOGIS-MRA)", 7],
        ["3.2", "International Recognition of CC – Certificates (CCRA)", 7],
        ["4", "Performance of Evaluation and Certification", 8],
        ["5", "Validity of the Certification Result", 8],
        ["6", "Publication", 9],
        ["B", "Certification Results", 10],
        ["1", "Executive Summary", 11],
        ["2", "Identification of the TOE", 12],
        ["3", "Security Policy", 16],
        ["4", "Assumptions and Clarification of Scope", 17],
        ["5", "Architectural Information", 18],
        ["6", "Documentation", 18],
        ["7", "IT Product Testing", 18],
        ["8", "Evaluated Configuration", 19],
        ["9", "Results of the Evaluation", 20],
        ["9.1", "CC specific results", 20],
        ["9.2", "Results of cryptographic assessment", 24],
        ["10", "Obligations and Notes for the Usage of the TOE", 29],
        ["11", "Security Target", 30],
        ["12", "Definitions", 30],
        ["12.1", "Acronyms", 30],
        ["12.2", "Glossary", 31],
        ["13", "Bibliography", 32],
        ["C", "Excerpts from the Criteria", 35],
        ["D", "Annexes", 36]
    ],
    "revisions": [],
    "bibliography": {
        "[1]": "Common Criteria for Information Technology Security Evaluation, Part 1: Introduction and general model - Version 3.1, Revision 5, April 2017 and Common Criteria for Information Technology Security Evaluation, Part 2: Security functional components, Version 3.1, Revision 5, April 2017 and Common Criteria for Information Technology Security Evaluation, Part 3: Security assurance components, Version 3.1, Revision 5, April 2017, https://www.commoncriteriaportal.org",
        "[2]": "Common Methodology for Information Technology Security Evaluation (CEM), Evaluation Methodology, Version 3.1, Rev. 5, April 2017, https://www.commoncriteriaportal.org",
        "[3]": "BSI certification: Scheme documentation describing the certification process (CC- Produkte) and Scheme documentation on requirements for the Evaluation Facility, approval and licencing (CC-Stellen), https://www.bsi.bund.de/zertifizierung",
        "[4]": "Application Notes and Interpretations of the Scheme (AIS) as relevant for the TOE, https://www.bsi.bund.de/AIS",
        "[5]": "German IT Security Certificates (BSI 7148), periodically updated list published also on the BSI Website, https://www.bsi.bund.de/zertifizierungsreporte",
        "[6]": "Confidential Security Target for BSI-DSZ-CC-1110-V2-2019, Version 2.9, 2019-05- 13, “Confidential Security Target IFX_CCI_000003h, IFX_CCI_000005h, IFX_CCI_000008h, IFX_CCI_00000Ch, IFX_CCI_000013h, IFX_CCI_000014h, IFX_CCI_000015h, IFX_CCI_00001Ch, IFX_CCI_00001Dh, IFX_CCI_000021h, IFX_CCI_000022h design step H13”, Infineon Technologies AG (confidential document)",
        "[7]": "Evaluation Technical Report for the Product BSI-DSZ-CC-1110-V2-2019, Version 2, 2019-06-14, “Evaluation Technical Report - Summary”, TÜV Informationstechnik GmbH, (confidential document)",
        "[8]": "Security IC Platform Protection Profile with Augmentation Packages Version 1.0, 13 January 2014, BSI-CC-PP-0084-2014",
        "[9]": "Public Security Target BSI-DSZ-CC-1110-V2-2019, Version 1.6, 2019-06-05, “Public Security Target IFX_CCI_000003h, IFX_CCI_000005h, IFX_CCI_000008h, IFX_CCI_00000Ch, IFX_CCI_000013h, IFX_CCI_000014h, IFX_CCI_000015h, IFX_CCI_00001Ch, IFX_CCI_00001Dh, IFX_CCI_000021h, IFX_CCI_000022h design step H13”, Infineon Technologies AG (sanitised public document)",
        "[10]": "ETR for composite evaluation according to AIS 36 for the Product BSI-DSZ-CC- 1110-V2-2019, Version 2, 2019-06-14, ETR for composite evaluation (EFC), TÜV Informationstechnik GmbH (confidential document)",
        "[11]": "16-Bit Security Controller - V01, Security Guidelines, Rev. 1.01-1956, Infineon Technologies AG, 2018-10-24",
        "[12]": "16-bit Security Controller – V01 Hardware Reference Manual, Rev. 6.1, Infineon Technologies AG, 2017-09-13",
        "[13]": "16-bit Security Controller – V01 Errata sheet, Rev. 8.1, Infineon Technologies AG, 2019-04-24",
        "[14]": "CL52 Asymmetric Crypto Library for Crypto@2304T RSA/ECC/Toolbox with included Errata Sheet of 10th May 2017, Rev. 2.06.003, Infineon Technologies AG, 2019-04-25 and CL52 Asymmetric Crypto Library for Crypto@2304T RSA/ECC/Toolbox”, Rev. 2.07.003, Infineon Technologies AG, 2019-04-25 ACL52-Crypto2304T-C65 Asymmetric Crypto Library, RSA / ECC / Toolbox, 16-bit Security Controller, User Interface, Version 2.08.007, Infineon Technologies AG, 2019-04-25",
        "[15]": "Crypto@2304T V3 User manual, Rev. 1.4.1, Infineon Technologies AG, 2014-11-10",
        "[16]": "16-bit Security Controller 65-nm Technology, Programmer's Reference Manual, Rev. 9.8, Infineon Technologies AG, 2018-03-19",
        "[17]": "Production and Personalization, 16-bit Security Controller in 65 nm, Rev. 3.4, Infineon Technologies AG, 2019-01-22",
        "[18]": "Hardware Support Library (HSL), chm-file, Rev. 01.22.4346 (as of 2016), Infineon Technologies AG and Hardware Support Library (HSL), chm-file, Rev. 02.01.6634 (as of 2017), Infineon Technologies AG and Hardware Support Library (HSL), chm-file, Rev. 03.11.8339 (as of 2018-07-12), Infineon Technologies AG and Hardware Support Library (HSL), chm-file, Rev. 03.12.8812 (as of 2018-11-23), Infineon Technologies AG",
        "[19]": "CIPURSETM Crypto Library, CCLX2xCIP v02.00.0004, CIPURSETM V2, Compliant to OSPTTM Alliance CIPURSETM V2 Cryptographic Protocol, User Interface, Revision 1.6, Infineon Technologies AG, 2018-02-02",
        "[20]": "SCL52 Symmetric Cryptogaphic Library for DES / AES, 16-bit Security Controller, User Interface, Version 2.02.010, 2016-12-09, Infineon Technologies AG and SCL52 Symmetric Cryptogaphic Library for DES / AES, 16-bit Security Controller, User Interface, Version 2.04.002, 2018-01-15, Infineon Technologies AG",
        "[21]": " HCL52-CPU-C65 Hash Crypto Library for CPU SHA 16-bit Security Controller User",
        "[22]": "Cryptographic Standards Compliance Verification, Version 1, 2019-03-27, TÜV Informationstechnik GmbH (confidential document)"
    },
    "other": {
        "certid": ""
    }
}
